aise_toolkit_demo/__init__.py
aise_toolkit_demo/__main__.py
aise_toolkit_demo/cli.py
aise_toolkit_demo/utils.py
aise_toolkit_demo/app/__init__.py
aise_toolkit_demo/app/app.py
aise_toolkit_demo/app/app_utiles.py
aise_toolkit_demo-0.5.dist-info/LICENSE
aise_toolkit_demo-0.5.dist-info/METADATA
aise_toolkit_demo-0.5.dist-info/WHEEL
aise_toolkit_demo-0.5.dist-info/entry_points.txt
aise_toolkit_demo-0.5.dist-info/top_level.txt
aise_toolkit_demo-0.5.dist-info/RECORD
