Metadata-Version: 2.1
Name: aise-toolkit-demo
Version: 0.5
Summary: A set of tools to assist developer to use AI
Author: Lei Xu
License: Apache-2.0
Project-URL: Homepage, https://github.com/ups216/aise-toolkit-demo
Project-URL: Changelog, https://github.com/ups216/aise-toolkit-demo/releases
Project-URL: Issues, https://github.com/ups216/aise-toolkit-demo/issues
Project-URL: CI, https://github.com/ups216/aise-toolkit-demo/actions
Classifier: License :: OSI Approved :: Apache Software License
Requires-Python: >=3.8
License-File: LICENSE
Requires-Dist: click
Provides-Extra: test
Requires-Dist: pytest ; extra == 'test'
